flowmotion/__init__.py
flowmotion/blocks/__init__.py
flowmotion/blocks/flow_block.py
flowmotion/blocks/flow_code.py
flowmotion/blocks/flow_text.py
flowmotion/blocks/formatter/__init__.py
flowmotion/blocks/formatter/flow_formatter.py
flowmotion/blocks/markup/__init__.py
flowmotion/blocks/markup/flow_markup.py
flowmotion/core/__init__.py
flowmotion/core/flow_group.py
flowmotion/core/flow_motion.py
flowmotion/core/flow_pointer.py
flowmotion/scenes/__init__.py
flowmotion/scenes/flow_scene.py
flowmotion/structs/__init__.py
flowmotion/structs/flow_array.py
flowmotion/structs/flow_stack.py
flowmotion/utils/__init__.py
flowmotion/utils/flow_utils.py
flowmotion-0.2.5.dist-info/licenses/LICENSE
flowmotion-0.2.5.dist-info/METADATA
flowmotion-0.2.5.dist-info/WHEEL
flowmotion-0.2.5.dist-info/top_level.txt
flowmotion-0.2.5.dist-info/RECORD
