Metadata-Version: 2.4
Name: flowmotion
Version: 0.2.5
Summary: A Manim-based animation library for visualizing data structures and algorithms.
Author: Mohammad Senan Ali
License-Expression: MIT
Requires-Python: >=3.12
License-File: LICENSE
Requires-Dist: manim>=0.19.0
Dynamic: license-file
